fastapi_stack_utils/__init__.py
fastapi_stack_utils/cli/__init__.py
fastapi_stack_utils/cli/cli.py
fastapi_stack_utils/cli/load_docker_env.py
fastapi_stack_utils/custom_base_settings.py
fastapi_stack_utils/exception_handler.py
fastapi_stack_utils/logging_config.py
fastapi_stack_utils/middleware.py
fastapi_stack_utils/py.typed
fastapi_stack_utils/route.py
fastapi_stack_utils/schemas/__init__.py
fastapi_stack_utils/schemas/http_exceptions.py
fastapi_stack_utils/uvloop.py
fastapi_stack_utils-0.8.7.dist-info/LICENSE
fastapi_stack_utils-0.8.7.dist-info/WHEEL
fastapi_stack_utils-0.8.7.dist-info/METADATA
fastapi_stack_utils-0.8.7.dist-info/entry_points.txt
fastapi_stack_utils-0.8.7.dist-info/RECORD
